chocomufin/__init__.py
chocomufin/classes.py
chocomufin/cli.py
chocomufin/funcs.py
chocomufin/functions.py
chocomufin/mufi.json
chocomufin/parsers.py
chocomufin-1.0.0.dist-info/LICENSE
chocomufin-1.0.0.dist-info/METADATA
chocomufin-1.0.0.dist-info/WHEEL
chocomufin-1.0.0.dist-info/entry_points.txt
chocomufin-1.0.0.dist-info/top_level.txt
chocomufin-1.0.0.dist-info/RECORD
