Metadata-Version: 2.1
Name: chocomufin
Version: 1.0.0
Summary: [CHaracter Ocr COordination for MUFI iN texts] A simple script to maintain a reasonable training set of HTR/OCR characters
Home-page: https://github.com/ponteineptique/choco-mufin
Author: Thibault Clerice
License: MIT
Platform: UNKNOWN
Classifier: License :: OSI Approved :: MIT License
Classifier: Programming Language :: Python
Classifier: Programming Language :: Python :: 3
Classifier: Programming Language :: Python :: 3.7
Classifier: Programming Language :: Python :: Implementation :: CPython
Classifier: Programming Language :: Python :: Implementation :: PyPy
Classifier: Topic :: Text Processing :: Linguistic
Requires-Python: >=3.6.0
License-File: LICENSE
Requires-Dist: Unidecode (==1.2.0)
Requires-Dist: click (>=8.0.0)
Requires-Dist: lxml (~=4.9.0)
Requires-Dist: mufidecode (==0.1.0)
Requires-Dist: regex (~=2022.4.24)
Requires-Dist: tabulate (==0.8.9)
Requires-Dist: tqdm (==4.61.1)
